{
  "id": "dayz",
  "name": "DayZ",
  "description": "DayZ dedicated server template using a direct SteamCMD install. It requires a real Steam account for app 223350 and starts the native Linux DayZServer binary without LinuxGSM cron/config side effects.",
  "defaultPort": 2302,
  "templateImage": "https://cdn.jsdelivr.net/gh/antonndev/ADCDn/dayz-logo.avif",
  "docker": {
    "image": "ghcr.io/ptero-eggs/steamcmd",
    "tag": "sniper",
    "ports": [
      2302,
      2303,
      2304,
      2305,
      8766,
      27016
    ],
    "portProtocols": {
      "2302": [
        "udp"
      ],
      "2303": [
        "udp"
      ],
      "2304": [
        "udp"
      ],
      "2305": [
        "udp"
      ],
      "8766": [
        "udp"
      ],
      "27016": [
        "udp"
      ]
    },
    "volumes": [
      "{BOT_DIR}:/home/container"
    ],
    "workdir": "/home/container",
    "env": {
      "APP_ID": "223350",
      "STEAM_USER": "",
      "STEAM_PASS": "",
      "STEAM_AUTH": "",
      "SERVER_NAME": "ADPanel DayZ Server",
      "SERVER_PASSWORD": "",
      "ADMIN_PASSWORD": "change-me",
      "MAX_PLAYERS": "60",
      "QUERY_PORT": "27016",
      "TZ": "Etc/UTC"
    },
    "command": "",
    "startupDisplay": "./DayZServer -config=serverDZ.cfg -port=2302 -BEpath=battleye -profiles=profiles -dologs -adminlog -netlog -freezeCheck",
    "adpanelStartup": "mkdir -p profiles && ./DayZServer -config=serverDZ.cfg -port={{SERVER_PORT}} -BEpath=battleye -profiles=profiles -dologs -adminlog -netlog -freezeCheck",
    "install": {
      "image": "ghcr.io/pterodactyl/installers:debian",
      "script": "#!/bin/bash\nset -Eeuo pipefail\napp_id=\"${APP_ID:-223350}\"\nif [ -z \"${STEAM_USER:-}\" ] || [ \"${STEAM_USER}\" = \"anonymous\" ]; then\n  echo \"DayZ app ${app_id} requires STEAM_USER and STEAM_PASS from a real Steam account.\"\n  exit 20\nfi\nif [ -z \"${STEAM_PASS:-}\" ]; then\n  echo \"STEAM_PASS is required for DayZ SteamCMD install.\"\n  exit 20\nfi\nmkdir -p /mnt/server/steamcmd /mnt/server/steamapps /mnt/server/profiles /mnt/server/.steam/sdk64 /mnt/server/.steam/sdk32\ninstall_steamcmd() {\n  rm -f /tmp/steamcmd.tar.gz\n  curl --retry 5 --retry-delay 2 --connect-timeout 20 -fsSL -o /tmp/steamcmd.tar.gz https://steamcdn-a.akamaihd.net/client/installer/steamcmd_linux.tar.gz\n  tar -xzf /tmp/steamcmd.tar.gz -C /mnt/server/steamcmd\n}\nif [ ! -x /mnt/server/steamcmd/steamcmd.sh ] || [ ! -x /mnt/server/steamcmd/linux32/steamcmd ]; then\n  rm -rf /mnt/server/steamcmd\n  mkdir -p /mnt/server/steamcmd\n  install_steamcmd\nfi\nlogin_args=(+login \"$STEAM_USER\" \"$STEAM_PASS\")\n[ -z \"${STEAM_AUTH:-}\" ] || login_args+=(\"$STEAM_AUTH\")\nfor attempt in 1 2 3 4; do\n  if HOME=/mnt/server /mnt/server/steamcmd/steamcmd.sh +force_install_dir /mnt/server \"${login_args[@]}\" +app_update \"$app_id\" validate +quit; then\n    break\n  fi\n  status=$?\n  if [ \"$attempt\" -eq 4 ]; then\n    exit \"$status\"\n  fi\n  rm -rf /mnt/server/steamcmd/package /mnt/server/steamcmd/linux32/steamcmd\n  install_steamcmd\n  sleep $((attempt * 15))\ndone\nif [ ! -x /mnt/server/DayZServer ]; then\n  echo \"DayZServer executable is missing after SteamCMD install. Check Steam credentials, Steam Guard and app ${app_id} access.\"\n  exit 30\nfi\ncp -f /mnt/server/steamcmd/linux64/steamclient.so /mnt/server/.steam/sdk64/steamclient.so || true\ncp -f /mnt/server/steamcmd/linux32/steamclient.so /mnt/server/.steam/sdk32/steamclient.so || true\nserver_name=\"${SERVER_NAME:-ADPanel DayZ Server}\"\nserver_password=\"${SERVER_PASSWORD:-}\"\nadmin_password=\"${ADMIN_PASSWORD:-change-me}\"\nmax_players=\"${MAX_PLAYERS:-60}\"\nquery_port=\"${QUERY_PORT:-27016}\"\nserver_name=\"${server_name//\\\"/}\"\nserver_password=\"${server_password//\\\"/}\"\nadmin_password=\"${admin_password//\\\"/}\"\nif [ ! -f /mnt/server/serverDZ.cfg ]; then\ncat > /mnt/server/serverDZ.cfg <<EOF\nhostname = \"$server_name\";\npassword = \"$server_password\";\npasswordAdmin = \"$admin_password\";\nmaxPlayers = $max_players;\nverifySignatures = 2;\nforceSameBuild = 1;\nsteamQueryPort = $query_port;\nEOF\nfi\nchmod -R a+rwX /mnt/server",
      "mountPath": "/mnt/server",
      "runtimePath": "/home/container",
      "minimumStorageMb": 35000,
      "timeoutSeconds": 3600
    },
    "restart": "unless-stopped",
    "console": {
      "type": "stdin"
    }
  },
  "documentation": [
    "https://developer.valvesoftware.com/wiki/Dedicated_Servers_List",
    "https://linuxgsm.com/servers/dayzserver/"
  ],
  "requirements": {
    "minimumRamMb": 4096,
    "recommendedRamMb": 8192,
    "minimumStorageMb": 35000,
    "requiresSteamAccountForInstall": true
  }
}
